Metadata-Version: 1.0
Name: vsndist
Version: 1.0
Summary: Gaussian & Binomial distributions
Home-page: UNKNOWN
Author: UNKNOWN
Author-email: UNKNOWN
License: UNKNOWN
Platform: UNKNOWN
